pasee/__init__.py
pasee/__main__.py
pasee/middlewares.py
pasee/pasee.py
pasee/serializers.py
pasee/storage_interface.py
pasee/utils.py
pasee/views.py
pasee/groups/__init__.py
pasee/groups/utils.py
pasee/groups/views.py
pasee/identity_providers/__init__.py
pasee/identity_providers/backend.py
pasee/identity_providers/kisee.py
pasee/identity_providers/twitter.py
pasee/identity_providers/utils.py
pasee/storage_backend/__init__.py
pasee/storage_backend/demo_backend/__init__.py
pasee/storage_backend/demo_backend/sqlite.py
pasee/storage_backend/pgsql_backend/__init__.py
pasee/storage_backend/pgsql_backend/pgsql.py
pasee/tokens/__init__.py
pasee/tokens/handlers.py
pasee/tokens/views.py
pasee/users/__init__.py
pasee/users/views.py
pasee/vendor/__init__.py
pasee/vendor/coreapi/__init__.py
pasee/vendor/coreapi/auth.py
pasee/vendor/coreapi/client.py
pasee/vendor/coreapi/compat.py
pasee/vendor/coreapi/document.py
pasee/vendor/coreapi/exceptions.py
pasee/vendor/coreapi/utils.py
pasee/vendor/coreapi/codecs/__init__.py
pasee/vendor/coreapi/codecs/base.py
pasee/vendor/coreapi/codecs/corejson.py
pasee/vendor/coreapi/codecs/display.py
pasee/vendor/coreapi/codecs/download.py
pasee/vendor/coreapi/codecs/jsondata.py
pasee/vendor/coreapi/codecs/python.py
pasee/vendor/coreapi/codecs/text.py
pasee/vendor/coreapi/transports/__init__.py
pasee/vendor/coreapi/transports/base.py
pasee/vendor/coreapi/transports/http.py
pasee/vendor/coreschema/__init__.py
pasee/vendor/coreschema/compat.py
pasee/vendor/coreschema/formats.py
pasee/vendor/coreschema/schemas.py
pasee/vendor/coreschema/utils.py
pasee/vendor/coreschema/encodings/__init__.py
pasee/vendor/coreschema/encodings/html.py
pasee/vendor/coreschema/encodings/jsonschema.py
pasee/vendor/itypes/__init__.py
pasee-21.4.1.dist-info/LICENSE
pasee-21.4.1.dist-info/METADATA
pasee-21.4.1.dist-info/WHEEL
pasee-21.4.1.dist-info/entry_points.txt
pasee-21.4.1.dist-info/top_level.txt
pasee-21.4.1.dist-info/RECORD
