Metadata-Version: 2.1
Name: pasee
Version: 21.4.1
Summary: HTTP server managing users.
Home-page: https://github.com/meltygroup/pasee
Author: Julien Palard
Author-email: julien@python.org
License: MIT License
Platform: UNKNOWN
Classifier: Development Status :: 5 - Production/Stable
Classifier: Intended Audience :: System Administrators
Classifier: License :: OSI Approved :: MIT License
Classifier: Programming Language :: Python :: 3.6
Classifier: Programming Language :: Python :: 3.7
Classifier: Programming Language :: Python :: 3.8
Classifier: Programming Language :: Python :: 3.9
Requires-Python: >=3.6
Requires-Dist: aioauth-client
Requires-Dist: aiohttp
Requires-Dist: aiohttp-cors
Requires-Dist: asyncpg
Requires-Dist: jinja2
Requires-Dist: pyjwt[crypto] (>=2.0.0)
Requires-Dist: pytoml
Requires-Dist: shortuuid
Provides-Extra: sentry
Requires-Dist: sentry-sdk (>=0.19) ; extra == 'sentry'
Requires-Dist: aiocontextvars ; extra == 'sentry'
